README.md
setup.py
tescomobile/__init__.py
tescomobile/tescomobile.py
tescomobile.egg-info/PKG-INFO
tescomobile.egg-info/SOURCES.txt
tescomobile.egg-info/dependency_links.txt
tescomobile.egg-info/requires.txt
tescomobile.egg-info/top_level.txt