Metadata-Version: 1.2
Name: tescomobile
Version: 0.1.0
Summary: Unofficial client for the Tesco Mobile account usage API
Home-page: https://github.com/adriankeenan/py-tescomobile
Author: Adrian Keenan
Author-email: git@adriankeenan.co.uk
License: WTFPL
Keywords: tesco,tescomobile
Platform: UNKNOWN
Requires-Python: >=2.7
